{
    "items": [
        {
            "kind": "youtube#playlistItem",
            "etag": "hApdJi0J06XqjI0tCIhXM_ghIYU",
            "id": "UExFRDREai1UNDNyTWRLN29oTlZXemNnOWMwX1RsNk1pOC42Qzk5MkEzQjVFQjYwRDA4",
            "snippet": {
                "publishedAt": "2022-05-15T15:50:21Z",
                "channelId": "UC4hprJdeUpKFnViDsCAYN6g",
                "title": "(مبادئ دروس العربية (1)/ (الكلمة والكلام)و(الأزمنة)، (أقسام الكلمة",
                "description": "رابط تحميل كتاب مبادئ \nhttps://drive.google.com/file/d/1-DpkZMe57tiQElYmTLYpgnarewKnBUBS/view?usp=sharing\n\n1   نسخة مراجعة ومصححة \n علي_هاني_العقرباوي المستوى الأول في سلسلة دراسة النحو، فأولًا مبادئ النحو ثم التوضيح على الآجرومية علي هاني ثم متن الآجرومية ثم التسهيل على الآجرومية ثم متممة الآجرومية ثم إعراب جزء عم ثم  النحو الوظيفي ثم قطر الندى ثم شذور الذهب ثم موصل الطلاب إلى قواعد الإعراب ثم ألفية ابن مالك بشرح ابن عقيل ثم  الألفية بشرح الأشموني ثم بشرح التصريح على التوضيح ثم المساعد شرح تسهيل الفوائد المتن لابن مالك والشرح لابن عقيل ثم  مغني اللبيب لابن هشام",
                "thumbnails": {
                    "default": {
                        "url": "https://i.ytimg.com/vi/9Vj8tSVrabk/default.jpg",
                        "width": 120,
                        "height": 90
                    },
                    "medium": {
                        "url": "https://i.ytimg.com/vi/9Vj8tSVrabk/mqdefault.jpg",
                        "width": 320,
                        "height": 180
                    },
                    "high": {
                        "url": "https://i.ytimg.com/vi/9Vj8tSVrabk/hqdefault.jpg",
                        "width": 480,
                        "height": 360
                    }
                },
                "channelTitle": "علي هاني العقرباوي",
                "playlistId": "PLED4Dj-T43rMdK7ohNVWzcg9c0_Tl6Mi8",
                "position": 0,
                "resourceId": {
                    "kind": "youtube#video",
                    "videoId": "9Vj8tSVrabk"
                },
                "videoOwnerChannelTitle": "علي هاني العقرباوي",
                "videoOwnerChannelId": "UC4hprJdeUpKFnViDsCAYN6g"
            },
            "contentDetails": {
                "videoId": "9Vj8tSVrabk",
                "videoPublishedAt": "2022-05-15T16:01:22Z"
            }
        },
        {
            "kind": "youtube#playlistItem",
            "etag": "HbWSPdajXlnMYwbOLnVyYn-67qw",
            "id": "UExFRDREai1UNDNyTWRLN29oTlZXemNnOWMwX1RsNk1pOC41NTZEOThBNThFOUVGQkVB",
            "snippet": {
                "publishedAt": "2022-05-16T02:48:13Z",
                "channelId": "UC4hprJdeUpKFnViDsCAYN6g",
                "title": "مبادئ دروس العربية (2)تتمة الاسم والفعل والحرف، وأقسام الأفعال ، والمبني للمعلوم والمجهول",
                "description": "رابط تحميل كتاب مبادئ https://drive.google.com/file/d/1-DpkZMe57tiQElYmTLYpgnarewKnBUBS/view?usp=sharing \n علي_هاني_العقرباوي المستوى الأول في سلسلة دراسة النحو، فأولًا مبادئ النحو ثم التوضيح على الآجرومية علي هاني ثم متن الآجرومية ثم التسهيل على الآجرومية ثم متممة الآجرومية ثم إعراب جزء عم ثم النحو الوظيفي ثم قطر الندى ثم شذور الذهب ثم موصل الطلاب إلى قواعد الإعراب ثم ألفية ابن مالك بشرح ابن عقيل ثم الألفية بشرح الأشموني ثم بشرح التصريح على التوضيح ثم المساعد شرح تسهيل الفوائد المتن لابن مالك والشرح لابن عقيل ثم مغني اللبيب لابن هشام",
                "thumbnails": {
                    "default": {
                        "url": "https://i.ytimg.com/vi/BY5I1I2gCAA/default.jpg",
                        "width": 120,
                        "height": 90
                    },
                    "medium": {
                        "url": "https://i.ytimg.com/vi/BY5I1I2gCAA/mqdefault.jpg",
                        "width": 320,
                        "height": 180
                    },
                    "high": {
                        "url": "https://i.ytimg.com/vi/BY5I1I2gCAA/hqdefault.jpg",
                        "width": 480,
                        "height": 360
                    },
                    "standard": {
                        "url": "https://i.ytimg.com/vi/BY5I1I2gCAA/sddefault.jpg",
                        "width": 640,
                        "height": 480
                    },
                    "maxres": {
                        "url": "https://i.ytimg.com/vi/BY5I1I2gCAA/maxresdefault.jpg",
                        "width": 1280,
                        "height": 720
                    }
                },
                "channelTitle": "علي هاني العقرباوي",
                "playlistId": "PLED4Dj-T43rMdK7ohNVWzcg9c0_Tl6Mi8",
                "position": 1,
                "resourceId": {
                    "kind": "youtube#video",
                    "videoId": "BY5I1I2gCAA"
                },
                "videoOwnerChannelTitle": "علي هاني العقرباوي",
                "videoOwnerChannelId": "UC4hprJdeUpKFnViDsCAYN6g"
            },
            "contentDetails": {
                "videoId": "BY5I1I2gCAA",
                "videoPublishedAt": "2022-05-16T02:54:18Z"
            }
        },
        {
            "kind": "youtube#playlistItem",
            "etag": "mJg8dbthpXtsEg6BZBdD3B3iwXw",
            "id": "UExFRDREai1UNDNyTWRLN29oTlZXemNnOWMwX1RsNk1pOC43NERCMDIzQzFBMERCMEE3",
            "snippet": {
                "publishedAt": "2022-05-20T22:11:52Z",
                "channelId": "UC4hprJdeUpKFnViDsCAYN6g",
                "title": "مبادئ دروس العربية(3)تتمة المبني للمعلوم والمبني للمجهول ، وتصريف الفعل الماضي مع الضمائر",
                "description": "رابط تحميل كتاب مبادئ \nhttps://drive.google.com/file/d/1-DpkZMe57tiQElYmTLYpgnarewKnBUBS/view?usp=sharing\n\n1   نسخة مراجعة ومصححة \n علي_هاني_العقرباوي المستوى الأول في سلسلة دراسة النحو، فأولًا مبادئ النحو ثم التوضيح على الآجرومية علي هاني ثم متن الآجرومية ثم التسهيل على الآجرومية ثم متممة الآجرومية ثم إعراب جزء عم ثم  النحو الوظيفي ثم قطر الندى ثم شذور الذهب ثم موصل الطلاب إلى قواعد الإعراب ثم ألفية ابن مالك بشرح ابن عقيل ثم  الألفية بشرح الأشموني ثم بشرح التصريح على التوضيح ثم المساعد شرح تسهيل الفوائد المتن لابن مالك والشرح لابن عقيل ثم  مغني اللبيب لابن هشام",
                "thumbnails": {
                    "default": {
                        "url": "https://i.ytimg.com/vi/AWNaJm2bhms/default.jpg",
                        "width": 120,
                        "height": 90
                    },
                    "medium": {
                        "url": "https://i.ytimg.com/vi/AWNaJm2bhms/mqdefault.jpg",
                        "width": 320,
                        "height": 180
                    },
                    "high": {
                        "url": "https://i.ytimg.com/vi/AWNaJm2bhms/hqdefault.jpg",
                        "width": 480,
                        "height": 360
                    }
                },
                "channelTitle": "علي هاني العقرباوي",
                "playlistId": "PLED4Dj-T43rMdK7ohNVWzcg9c0_Tl6Mi8",
                "position": 2,
                "resourceId": {
                    "kind": "youtube#video",
                    "videoId": "AWNaJm2bhms"
                },
                "videoOwnerChannelTitle": "علي هاني العقرباوي",
                "videoOwnerChannelId": "UC4hprJdeUpKFnViDsCAYN6g"
            },
            "contentDetails": {
                "videoId": "AWNaJm2bhms",
                "videoPublishedAt": "2022-05-20T22:33:21Z"
            }
        },
        {
            "kind": "youtube#playlistItem",
            "etag": "vPHtUw1_Ae1Y5rleQePnunSAC5c",
            "id": "UExFRDREai1UNDNyTWRLN29oTlZXemNnOWMwX1RsNk1pOC5GNjAwN0Y0QTFGOTVDMEMy",
            "snippet": {
                "publishedAt": "2022-05-20T22:12:52Z",
                "channelId": "UC4hprJdeUpKFnViDsCAYN6g",
                "title": "مبادئ دروس العربية )(4) تتمة تصريف الفعل الماضي مع الضمائر، وتصريف الفعل المضارع مع الضمائر",
                "description": "رابط تحميل كتاب مبادئ \nhttps://drive.google.com/file/d/1-DpkZMe57tiQElYmTLYpgnarewKnBUBS/view?usp=sharing\n\n1   نسخة مراجعة ومصححة \n علي_هاني_العقرباوي المستوى الأول في سلسلة دراسة النحو، فأولًا مبادئ النحو ثم التوضيح على الآجرومية علي هاني ثم متن الآجرومية ثم التسهيل على الآجرومية ثم متممة الآجرومية ثم إعراب جزء عم ثم  النحو الوظيفي ثم قطر الندى ثم شذور الذهب ثم موصل الطلاب إلى قواعد الإعراب ثم ألفية ابن مالك بشرح ابن عقيل ثم  الألفية بشرح الأشموني ثم بشرح التصريح على التوضيح ثم المساعد شرح تسهيل الفوائد المتن لابن مالك والشرح لابن عقيل ثم  مغني اللبيب لابن هشام",
                "thumbnails": {
                    "default": {
                        "url": "https://i.ytimg.com/vi/_kwNUwFklnY/default.jpg",
                        "width": 120,
                        "height": 90
                    },
                    "medium": {
                        "url": "https://i.ytimg.com/vi/_kwNUwFklnY/mqdefault.jpg",
                        "width": 320,
                        "height": 180
                    },
                    "high": {
                        "url": "https://i.ytimg.com/vi/_kwNUwFklnY/hqdefault.jpg",
                        "width": 480,
                        "height": 360
                    }
                },
                "channelTitle": "علي هاني العقرباوي",
                "playlistId": "PLED4Dj-T43rMdK7ohNVWzcg9c0_Tl6Mi8",
                "position": 3,
                "resourceId": {
                    "kind": "youtube#video",
                    "videoId": "_kwNUwFklnY"
                },
                "videoOwnerChannelTitle": "علي هاني العقرباوي",
                "videoOwnerChannelId": "UC4hprJdeUpKFnViDsCAYN6g"
            },
            "contentDetails": {
                "videoId": "_kwNUwFklnY",
                "videoPublishedAt": "2022-05-20T22:12:02Z"
            }
        },
        {
            "kind": "youtube#playlistItem",
            "etag": "a2JGPOVdQsKLSt15n0F4sNRWawg",
            "id": "UExFRDREai1UNDNyTWRLN29oTlZXemNnOWMwX1RsNk1pOC5CQkEwRDA0MDkwNUM2MDY1",
            "snippet": {
                "publishedAt": "2022-05-20T22:14:02Z",
                "channelId": "UC4hprJdeUpKFnViDsCAYN6g",
                "title": "مبادئ دروس العربية (5) تصريف الأمر مع الضمائر ، وأحوال آخر الفعل الماضي",
                "description": "رابط تحميل كتاب مبادئ \nhttps://drive.google.com/file/d/1-DpkZMe57tiQElYmTLYpgnarewKnBUBS/view?usp=sharing\n\n1   نسخة مراجعة ومصححة \n علي_هاني_العقرباوي المستوى الأول في سلسلة دراسة النحو، فأولًا مبادئ النحو ثم التوضيح على الآجرومية علي هاني ثم متن الآجرومية ثم التسهيل على الآجرومية ثم متممة الآجرومية ثم إعراب جزء عم ثم  النحو الوظيفي ثم قطر الندى ثم شذور الذهب ثم موصل الطلاب إلى قواعد الإعراب ثم ألفية ابن مالك بشرح ابن عقيل ثم  الألفية بشرح الأشموني ثم بشرح التصريح على التوضيح ثم المساعد شرح تسهيل الفوائد المتن لابن مالك والشرح لابن عقيل ثم  مغني اللبيب لابن هشام",
                "thumbnails": {
                    "default": {
                        "url": "https://i.ytimg.com/vi/Eb6hQGhjico/default.jpg",
                        "width": 120,
                        "height": 90
                    },
                    "medium": {
                        "url": "https://i.ytimg.com/vi/Eb6hQGhjico/mqdefault.jpg",
                        "width": 320,
                        "height": 180
                    },
                    "high": {
                        "url": "https://i.ytimg.com/vi/Eb6hQGhjico/hqdefault.jpg",
                        "width": 480,
                        "height": 360
                    }
                },
                "channelTitle": "علي هاني العقرباوي",
                "playlistId": "PLED4Dj-T43rMdK7ohNVWzcg9c0_Tl6Mi8",
                "position": 4,
                "resourceId": {
                    "kind": "youtube#video",
                    "videoId": "Eb6hQGhjico"
                },
                "videoOwnerChannelTitle": "علي هاني العقرباوي",
                "videoOwnerChannelId": "UC4hprJdeUpKFnViDsCAYN6g"
            },
            "contentDetails": {
                "videoId": "Eb6hQGhjico",
                "videoPublishedAt": "2022-05-20T22:13:47Z"
            }
        },
        {
            "kind": "youtube#playlistItem",
            "etag": "KsiygDWWADhZAOik7Ooz400UWGI",
            "id": "UExFRDREai1UNDNyTWRLN29oTlZXemNnOWMwX1RsNk1pOC4wNEU1MTI4NkZEMzVBN0JF",
            "snippet": {
                "publishedAt": "2022-05-20T22:15:42Z",
                "channelId": "UC4hprJdeUpKFnViDsCAYN6g",
                "title": "مبادئ دروس العربية (6) أحوال آخر فعل الأمر، وأحوال إعراب الفعل المضارع",
                "description": "رابط تحميل كتاب مبادئ \nhttps://drive.google.com/file/d/1-DpkZMe57tiQElYmTLYpgnarewKnBUBS/view?usp=sharing\n\n1   نسخة مراجعة ومصححة \n علي_هاني_العقرباوي المستوى الأول في سلسلة دراسة النحو، فأولًا مبادئ النحو ثم التوضيح على الآجرومية علي هاني ثم متن الآجرومية ثم التسهيل على الآجرومية ثم متممة الآجرومية ثم إعراب جزء عم ثم  النحو الوظيفي ثم قطر الندى ثم شذور الذهب ثم موصل الطلاب إلى قواعد الإعراب ثم ألفية ابن مالك بشرح ابن عقيل ثم  الألفية بشرح الأشموني ثم بشرح التصريح على التوضيح ثم المساعد شرح تسهيل الفوائد المتن لابن مالك والشرح لابن عقيل ثم  مغني اللبيب لابن هشام",
                "thumbnails": {
                    "default": {
                        "url": "https://i.ytimg.com/vi/WSGJiquRSNc/default.jpg",
                        "width": 120,
                        "height": 90
                    },
                    "medium": {
                        "url": "https://i.ytimg.com/vi/WSGJiquRSNc/mqdefault.jpg",
                        "width": 320,
                        "height": 180
                    },
                    "high": {
                        "url": "https://i.ytimg.com/vi/WSGJiquRSNc/hqdefault.jpg",
                        "width": 480,
                        "height": 360
                    }
                },
                "channelTitle": "علي هاني العقرباوي",
                "playlistId": "PLED4Dj-T43rMdK7ohNVWzcg9c0_Tl6Mi8",
                "position": 5,
                "resourceId": {
                    "kind": "youtube#video",
                    "videoId": "WSGJiquRSNc"
                },
                "videoOwnerChannelTitle": "علي هاني العقرباوي",
                "videoOwnerChannelId": "UC4hprJdeUpKFnViDsCAYN6g"
            },
            "contentDetails": {
                "videoId": "WSGJiquRSNc",
                "videoPublishedAt": "2022-05-20T22:15:08Z"
            }
        },
        {
            "kind": "youtube#playlistItem",
            "etag": "SbC27eLh0S-RMm2YSpWY0muocx0",
            "id": "UExFRDREai1UNDNyTWRLN29oTlZXemNnOWMwX1RsNk1pOC4wMTYxQzVBRDI1NEVDQUZE",
            "snippet": {
                "publishedAt": "2022-05-20T22:29:59Z",
                "channelId": "UC4hprJdeUpKFnViDsCAYN6g",
                "title": "مبادئ دروس العربية (7) الفعل المضارع المنصوب والمجزوم",
                "description": "رابط تحميل كتاب مبادئ \nhttps://drive.google.com/file/d/1-DpkZMe57tiQElYmTLYpgnarewKnBUBS/view?usp=sharing\n\n1   نسخة مراجعة ومصححة \n علي_هاني_العقرباوي المستوى الأول في سلسلة دراسة النحو، فأولًا مبادئ النحو ثم التوضيح على الآجرومية علي هاني ثم متن الآجرومية ثم التسهيل على الآجرومية ثم متممة الآجرومية ثم إعراب جزء عم ثم  النحو الوظيفي ثم قطر الندى ثم شذور الذهب ثم موصل الطلاب إلى قواعد الإعراب ثم ألفية ابن مالك بشرح ابن عقيل ثم  الألفية بشرح الأشموني ثم بشرح التصريح على التوضيح ثم المساعد شرح تسهيل الفوائد المتن لابن مالك والشرح لابن عقيل ثم  مغني اللبيب لابن هشام",
                "thumbnails": {
                    "default": {
                        "url": "https://i.ytimg.com/vi/DznOyfXC_fI/default.jpg",
                        "width": 120,
                        "height": 90
                    },
                    "medium": {
                        "url": "https://i.ytimg.com/vi/DznOyfXC_fI/mqdefault.jpg",
                        "width": 320,
                        "height": 180
                    },
                    "high": {
                        "url": "https://i.ytimg.com/vi/DznOyfXC_fI/hqdefault.jpg",
                        "width": 480,
                        "height": 360
                    }
                },
                "channelTitle": "علي هاني العقرباوي",
                "playlistId": "PLED4Dj-T43rMdK7ohNVWzcg9c0_Tl6Mi8",
                "position": 6,
                "resourceId": {
                    "kind": "youtube#video",
                    "videoId": "DznOyfXC_fI"
                },
                "videoOwnerChannelTitle": "علي هاني العقرباوي",
                "videoOwnerChannelId": "UC4hprJdeUpKFnViDsCAYN6g"
            },
            "contentDetails": {
                "videoId": "DznOyfXC_fI",
                "videoPublishedAt": "2022-05-20T22:49:25Z"
            }
        },
        {
            "kind": "youtube#playlistItem",
            "etag": "sQ8EBSwuGPfEKww0Y1rWGQ2KkQE",
            "id": "UExFRDREai1UNDNyTWRLN29oTlZXemNnOWMwX1RsNk1pOC4zMUEyMkQwOTk0NTg4MDgw",
            "snippet": {
                "publishedAt": "2022-05-21T00:13:19Z",
                "channelId": "UC4hprJdeUpKFnViDsCAYN6g",
                "title": "مبادئ دروس العربية (8) المفرد والمثنى والجمع، والمذكر والمؤنيث، وإعراب الاسم ، والفاعل",
                "description": "رابط تحميل كتاب مبادئ \nhttps://drive.google.com/file/d/1-DpkZMe57tiQElYmTLYpgnarewKnBUBS/view?usp=sharing\n\n1   نسخة مراجعة ومصححة \n علي_هاني_العقرباوي المستوى الأول في سلسلة دراسة النحو، فأولًا مبادئ النحو ثم التوضيح على الآجرومية علي هاني ثم متن الآجرومية ثم التسهيل على الآجرومية ثم متممة الآجرومية ثم إعراب جزء عم ثم  النحو الوظيفي ثم قطر الندى ثم شذور الذهب ثم موصل الطلاب إلى قواعد الإعراب ثم ألفية ابن مالك بشرح ابن عقيل ثم  الألفية بشرح الأشموني ثم بشرح التصريح على التوضيح ثم المساعد شرح تسهيل الفوائد المتن لابن مالك والشرح لابن عقيل ثم  مغني اللبيب لابن هشام",
                "thumbnails": {
                    "default": {
                        "url": "https://i.ytimg.com/vi/R1wn5RhZJn4/default.jpg",
                        "width": 120,
                        "height": 90
                    },
                    "medium": {
                        "url": "https://i.ytimg.com/vi/R1wn5RhZJn4/mqdefault.jpg",
                        "width": 320,
                        "height": 180
                    },
                    "high": {
                        "url": "https://i.ytimg.com/vi/R1wn5RhZJn4/hqdefault.jpg",
                        "width": 480,
                        "height": 360
                    }
                },
                "channelTitle": "علي هاني العقرباوي",
                "playlistId": "PLED4Dj-T43rMdK7ohNVWzcg9c0_Tl6Mi8",
                "position": 7,
                "resourceId": {
                    "kind": "youtube#video",
                    "videoId": "R1wn5RhZJn4"
                },
                "videoOwnerChannelTitle": "علي هاني العقرباوي",
                "videoOwnerChannelId": "UC4hprJdeUpKFnViDsCAYN6g"
            },
            "contentDetails": {
                "videoId": "R1wn5RhZJn4",
                "videoPublishedAt": "2022-05-21T00:21:45Z"
            }
        },
        {
            "kind": "youtube#playlistItem",
            "etag": "2iaU09MwFpytLzcojUfXaQlfxLY",
            "id": "UExFRDREai1UNDNyTWRLN29oTlZXemNnOWMwX1RsNk1pOC42QzdBMzlBQzQzRjQ0QkQy",
            "snippet": {
                "publishedAt": "2022-05-21T00:16:03Z",
                "channelId": "UC4hprJdeUpKFnViDsCAYN6g",
                "title": "مبادئ دروس العربية(9) نائب الفاعل،تأنيث الفعل المبني للمعلوم والمجهول",
                "description": "رابط تحميل كتاب مبادئ \nhttps://drive.google.com/file/d/1-DpkZMe57tiQElYmTLYpgnarewKnBUBS/view?usp=sharing\n\n1   نسخة مراجعة ومصححة \n علي_هاني_العقرباوي المستوى الأول في سلسلة دراسة النحو، فأولًا مبادئ النحو ثم التوضيح على الآجرومية علي هاني ثم متن الآجرومية ثم التسهيل على الآجرومية ثم متممة الآجرومية ثم إعراب جزء عم ثم  النحو الوظيفي ثم قطر الندى ثم شذور الذهب ثم موصل الطلاب إلى قواعد الإعراب ثم ألفية ابن مالك بشرح ابن عقيل ثم  الألفية بشرح الأشموني ثم بشرح التصريح على التوضيح ثم المساعد شرح تسهيل الفوائد المتن لابن مالك والشرح لابن عقيل ثم  مغني اللبيب لابن هشام",
                "thumbnails": {
                    "default": {
                        "url": "https://i.ytimg.com/vi/o5qjcQIbUvc/default.jpg",
                        "width": 120,
                        "height": 90
                    },
                    "medium": {
                        "url": "https://i.ytimg.com/vi/o5qjcQIbUvc/mqdefault.jpg",
                        "width": 320,
                        "height": 180
                    },
                    "high": {
                        "url": "https://i.ytimg.com/vi/o5qjcQIbUvc/hqdefault.jpg",
                        "width": 480,
                        "height": 360
                    }
                },
                "channelTitle": "علي هاني العقرباوي",
                "playlistId": "PLED4Dj-T43rMdK7ohNVWzcg9c0_Tl6Mi8",
                "position": 8,
                "resourceId": {
                    "kind": "youtube#video",
                    "videoId": "o5qjcQIbUvc"
                },
                "videoOwnerChannelTitle": "علي هاني العقرباوي",
                "videoOwnerChannelId": "UC4hprJdeUpKFnViDsCAYN6g"
            },
            "contentDetails": {
                "videoId": "o5qjcQIbUvc",
                "videoPublishedAt": "2022-05-21T00:22:53Z"
            }
        },
        {
            "kind": "youtube#playlistItem",
            "etag": "qVukg-5fG9NZhQy4YnvchiOfX0U",
            "id": "UExFRDREai1UNDNyTWRLN29oTlZXemNnOWMwX1RsNk1pOC41OURENDc2NEM1MDI5Mjky",
            "snippet": {
                "publishedAt": "2022-05-21T00:25:59Z",
                "channelId": "UC4hprJdeUpKFnViDsCAYN6g",
                "title": "مبادئ دروس العربية (10) المبتدأ والخبر ، وكان وأخواتها",
                "description": "رابط تحميل كتاب مبادئ \nhttps://drive.google.com/file/d/1-DpkZMe57tiQElYmTLYpgnarewKnBUBS/view?usp=sharing\n\n1   نسخة مراجعة ومصححة \n علي_هاني_العقرباوي المستوى الأول في سلسلة دراسة النحو، فأولًا مبادئ النحو ثم التوضيح على الآجرومية علي هاني ثم متن الآجرومية ثم التسهيل على الآجرومية ثم متممة الآجرومية ثم إعراب جزء عم ثم  النحو الوظيفي ثم قطر الندى ثم شذور الذهب ثم موصل الطلاب إلى قواعد الإعراب ثم ألفية ابن مالك بشرح ابن عقيل ثم  الألفية بشرح الأشموني ثم بشرح التصريح على التوضيح ثم المساعد شرح تسهيل الفوائد المتن لابن مالك والشرح لابن عقيل ثم  مغني اللبيب لابن هشام",
                "thumbnails": {
                    "default": {
                        "url": "https://i.ytimg.com/vi/i7VWLbF1Bbk/default.jpg",
                        "width": 120,
                        "height": 90
                    },
                    "medium": {
                        "url": "https://i.ytimg.com/vi/i7VWLbF1Bbk/mqdefault.jpg",
                        "width": 320,
                        "height": 180
                    },
                    "high": {
                        "url": "https://i.ytimg.com/vi/i7VWLbF1Bbk/hqdefault.jpg",
                        "width": 480,
                        "height": 360
                    }
                },
                "channelTitle": "علي هاني العقرباوي",
                "playlistId": "PLED4Dj-T43rMdK7ohNVWzcg9c0_Tl6Mi8",
                "position": 9,
                "resourceId": {
                    "kind": "youtube#video",
                    "videoId": "i7VWLbF1Bbk"
                },
                "videoOwnerChannelTitle": "علي هاني العقرباوي",
                "videoOwnerChannelId": "UC4hprJdeUpKFnViDsCAYN6g"
            },
            "contentDetails": {
                "videoId": "i7VWLbF1Bbk",
                "videoPublishedAt": "2022-05-21T00:42:10Z"
            }
        },
        {
            "kind": "youtube#playlistItem",
            "etag": "ngm5U6baEvqd-bhMTgJcoz-4Y4A",
            "id": "UExFRDREai1UNDNyTWRLN29oTlZXemNnOWMwX1RsNk1pOC4wRjhFM0MxMTU1MEUzQ0VB",
            "snippet": {
                "publishedAt": "2022-05-21T00:29:12Z",
                "channelId": "UC4hprJdeUpKFnViDsCAYN6g",
                "title": "مبادئ دروس العربية (11) (إنَّ) وأخواتها، والمفعول به",
                "description": "رابط تحميل كتاب مبادئ \nhttps://drive.google.com/file/d/1-DpkZMe57tiQElYmTLYpgnarewKnBUBS/view?usp=sharing\n\n1   نسخة مراجعة ومصححة \n علي_هاني_العقرباوي المستوى الأول في سلسلة دراسة النحو، فأولًا مبادئ النحو ثم التوضيح على الآجرومية علي هاني ثم متن الآجرومية ثم التسهيل على الآجرومية ثم متممة الآجرومية ثم إعراب جزء عم ثم  النحو الوظيفي ثم قطر الندى ثم شذور الذهب ثم موصل الطلاب إلى قواعد الإعراب ثم ألفية ابن مالك بشرح ابن عقيل ثم  الألفية بشرح الأشموني ثم بشرح التصريح على التوضيح ثم المساعد شرح تسهيل الفوائد المتن لابن مالك والشرح لابن عقيل ثم  مغني اللبيب لابن هشام",
                "thumbnails": {
                    "default": {
                        "url": "https://i.ytimg.com/vi/ERWnG4fVglc/default.jpg",
                        "width": 120,
                        "height": 90
                    },
                    "medium": {
                        "url": "https://i.ytimg.com/vi/ERWnG4fVglc/mqdefault.jpg",
                        "width": 320,
                        "height": 180
                    },
                    "high": {
                        "url": "https://i.ytimg.com/vi/ERWnG4fVglc/hqdefault.jpg",
                        "width": 480,
                        "height": 360
                    }
                },
                "channelTitle": "علي هاني العقرباوي",
                "playlistId": "PLED4Dj-T43rMdK7ohNVWzcg9c0_Tl6Mi8",
                "position": 10,
                "resourceId": {
                    "kind": "youtube#video",
                    "videoId": "ERWnG4fVglc"
                },
                "videoOwnerChannelTitle": "علي هاني العقرباوي",
                "videoOwnerChannelId": "UC4hprJdeUpKFnViDsCAYN6g"
            },
            "contentDetails": {
                "videoId": "ERWnG4fVglc",
                "videoPublishedAt": "2022-05-21T00:31:41Z"
            }
        },
        {
            "kind": "youtube#playlistItem",
            "etag": "WQ5xY-LEK-Je1auG-oi4xj8T4Xc",
            "id": "UExFRDREai1UNDNyTWRLN29oTlZXemNnOWMwX1RsNk1pOC5CNTZFOTNGQzZEODg1RUQx",
            "snippet": {
                "publishedAt": "2022-05-21T00:33:47Z",
                "channelId": "UC4hprJdeUpKFnViDsCAYN6g",
                "title": "مبادئ دروس العربية(12) الظرف، حروف الجر، المضاف والمضاف إليه",
                "description": "رابط تحميل كتاب مبادئ \nhttps://drive.google.com/file/d/1-DpkZMe57tiQElYmTLYpgnarewKnBUBS/view?usp=sharing\n\n1   نسخة مراجعة ومصححة \n علي_هاني_العقرباوي المستوى الأول في سلسلة دراسة النحو، فأولًا مبادئ النحو ثم التوضيح على الآجرومية علي هاني ثم متن الآجرومية ثم التسهيل على الآجرومية ثم متممة الآجرومية ثم إعراب جزء عم ثم  النحو الوظيفي ثم قطر الندى ثم شذور الذهب ثم موصل الطلاب إلى قواعد الإعراب ثم ألفية ابن مالك بشرح ابن عقيل ثم  الألفية بشرح الأشموني ثم بشرح التصريح على التوضيح ثم المساعد شرح تسهيل الفوائد المتن لابن مالك والشرح لابن عقيل ثم  مغني اللبيب لابن هشام",
                "thumbnails": {
                    "default": {
                        "url": "https://i.ytimg.com/vi/KUMM0Tv7yRw/default.jpg",
                        "width": 120,
                        "height": 90
                    },
                    "medium": {
                        "url": "https://i.ytimg.com/vi/KUMM0Tv7yRw/mqdefault.jpg",
                        "width": 320,
                        "height": 180
                    },
                    "high": {
                        "url": "https://i.ytimg.com/vi/KUMM0Tv7yRw/hqdefault.jpg",
                        "width": 480,
                        "height": 360
                    }
                },
                "channelTitle": "علي هاني العقرباوي",
                "playlistId": "PLED4Dj-T43rMdK7ohNVWzcg9c0_Tl6Mi8",
                "position": 11,
                "resourceId": {
                    "kind": "youtube#video",
                    "videoId": "KUMM0Tv7yRw"
                },
                "videoOwnerChannelTitle": "علي هاني العقرباوي",
                "videoOwnerChannelId": "UC4hprJdeUpKFnViDsCAYN6g"
            },
            "contentDetails": {
                "videoId": "KUMM0Tv7yRw",
                "videoPublishedAt": "2022-05-21T00:39:01Z"
            }
        },
        {
            "kind": "youtube#playlistItem",
            "etag": "akzrLJ87boQQWcN5jxHfDYo9jBw",
            "id": "UExFRDREai1UNDNyTWRLN29oTlZXemNnOWMwX1RsNk1pOC5CNTcxMDQ0NThBNzMxODYz",
            "snippet": {
                "publishedAt": "2022-05-21T00:35:40Z",
                "channelId": "UC4hprJdeUpKFnViDsCAYN6g",
                "title": "مبادئ دروس العربية(13) النعت ، وأحرف العطف",
                "description": "رابط تحميل كتاب مبادئ \nhttps://drive.google.com/file/d/1-DpkZMe57tiQElYmTLYpgnarewKnBUBS/view?usp=sharing\n\n1   نسخة مراجعة ومصححة \n علي_هاني_العقرباوي المستوى الأول في سلسلة دراسة النحو، فأولًا مبادئ النحو ثم التوضيح على الآجرومية علي هاني ثم متن الآجرومية ثم التسهيل على الآجرومية ثم متممة الآجرومية ثم إعراب جزء عم ثم  النحو الوظيفي ثم قطر الندى ثم شذور الذهب ثم موصل الطلاب إلى قواعد الإعراب ثم ألفية ابن مالك بشرح ابن عقيل ثم  الألفية بشرح الأشموني ثم بشرح التصريح على التوضيح ثم المساعد شرح تسهيل الفوائد المتن لابن مالك والشرح لابن عقيل ثم  مغني اللبيب لابن هشام",
                "thumbnails": {
                    "default": {
                        "url": "https://i.ytimg.com/vi/4swx2I9Q-5s/default.jpg",
                        "width": 120,
                        "height": 90
                    },
                    "medium": {
                        "url": "https://i.ytimg.com/vi/4swx2I9Q-5s/mqdefault.jpg",
                        "width": 320,
                        "height": 180
                    },
                    "high": {
                        "url": "https://i.ytimg.com/vi/4swx2I9Q-5s/hqdefault.jpg",
                        "width": 480,
                        "height": 360
                    },
                    "standard": {
                        "url": "https://i.ytimg.com/vi/4swx2I9Q-5s/sddefault.jpg",
                        "width": 640,
                        "height": 480
                    },
                    "maxres": {
                        "url": "https://i.ytimg.com/vi/4swx2I9Q-5s/maxresdefault.jpg",
                        "width": 1280,
                        "height": 720
                    }
                },
                "channelTitle": "علي هاني العقرباوي",
                "playlistId": "PLED4Dj-T43rMdK7ohNVWzcg9c0_Tl6Mi8",
                "position": 12,
                "resourceId": {
                    "kind": "youtube#video",
                    "videoId": "4swx2I9Q-5s"
                },
                "videoOwnerChannelTitle": "علي هاني العقرباوي",
                "videoOwnerChannelId": "UC4hprJdeUpKFnViDsCAYN6g"
            },
            "contentDetails": {
                "videoId": "4swx2I9Q-5s",
                "videoPublishedAt": "2022-05-21T00:36:07Z"
            }
        }
    ],
    "title": "دروة  مبادئ  دروس العربية",
    "nav": "مبادئ  دروس العربية",
    "id": "1_1"
}